heroku_git_fs/__init__.py
heroku_git_fs-1.0.0.dist-info/DESCRIPTION.rst
heroku_git_fs-1.0.0.dist-info/METADATA
heroku_git_fs-1.0.0.dist-info/RECORD
heroku_git_fs-1.0.0.dist-info/WHEEL
heroku_git_fs-1.0.0.dist-info/metadata.json
heroku_git_fs-1.0.0.dist-info/top_level.txt
