Metadata-Version: 2.0
Name: heroku-git-fs
Version: 1.0.0
Summary: A python module/class to sync data to a git repository. Designed for ephemeral filesystems.
Home-page: https://github.com/ev1l0rd/heroku_git_fs
Author: Valentijn "ev1l0rd"
Author-email: contact@ev1l0rd.info
License: GNU GPLv3.0
Project-URL: Documentation, http://heroku-git-fs.readthedocs.io/en/latest/
Platform: UNKNOWN
Requires-Dist: GitPython
